CHANGES.rst
DESCRIPTION.rst
MANIFEST.in
README.md
setup.py
src/gifr/__init__.py
src/gifr/asr.py
src/gifr/asr_text_generation.py
src/gifr/colors.py
src/gifr/common.py
src/gifr/fonts.py
src/gifr/image_classification.py
src/gifr/image_segmentation.py
src/gifr/object_detection.py
src/gifr/text_classification.py
src/gifr/text_generation.py
src/gifr.egg-info/PKG-INFO
src/gifr.egg-info/SOURCES.txt
src/gifr.egg-info/dependency_links.txt
src/gifr.egg-info/entry_points.txt
src/gifr.egg-info/requires.txt
src/gifr.egg-info/top_level.txt