Metadata-Version: 1.1
Name: gifr
Version: 0.0.6
Summary: gradio interfaces for Deep Learning Docker images that use Redis for receiving data to make predictions on.
Home-page: https://github.com/waikato-datamining/gifr
Author: Peter Reutemann
Author-email: fracpete@waikato.ac.nz
License: MIT License
Platform: UNKNOWN
Classifier: Development Status :: 4 - Beta
Classifier: License :: OSI Approved :: MIT License
Classifier: Topic :: Utilities
Classifier: Programming Language :: Python :: 3
